saxon_he/saxon-he-11.4.jar
saxon_he/saxon-he-test-11.4.jar
saxon_he/saxon-he-xqj-11.4.jar
saxon_he/doc/index.html
saxon_he/doc/saxondocs.css
saxon_he/doc/img/logo_crop-mid-blue-background.gif
saxon_he/doc/img/saxonica_logo.gif
saxon_he/lib/jline-2.14.6.jar
saxon_he/lib/xmlresolver-4.4.3-data.jar
saxon_he/lib/xmlresolver-4.4.3.jar
saxon_he/notices/JAMESCLARK.txt
saxon_he/notices/JLINE2.txt
saxon_he/notices/LICENSE.txt
saxonhe4py/__init__.py
saxonhe4py/_version.py
saxonhe4py-11.4.0.dist-info/LICENSE
saxonhe4py-11.4.0.dist-info/METADATA
saxonhe4py-11.4.0.dist-info/WHEEL
saxonhe4py-11.4.0.dist-info/top_level.txt
saxonhe4py-11.4.0.dist-info/RECORD
